irekua_database/__init__.py
irekua_database/apps.py
irekua_database/signals.py
irekua_database/utils.py
irekua_database/migrations/0001_initial.py
irekua_database/migrations/__init__.py
irekua_database/models/__init__.py
irekua_database/models/base.py
irekua_database/models/licences.py
irekua_database/models/annotations/__init__.py
irekua_database/models/annotations/annotation_tools.py
irekua_database/models/annotations/annotation_votes.py
irekua_database/models/annotations/annotations.py
irekua_database/models/data_collections/__init__.py
irekua_database/models/data_collections/collection_devices.py
irekua_database/models/data_collections/collection_sites.py
irekua_database/models/data_collections/collection_users.py
irekua_database/models/data_collections/data_collections.py
irekua_database/models/data_collections/metacollections.py
irekua_database/models/devices/__init__.py
irekua_database/models/devices/device_brands.py
irekua_database/models/devices/devices.py
irekua_database/models/devices/physical_devices.py
irekua_database/models/items/__init__.py
irekua_database/models/items/items.py
irekua_database/models/items/secondary_items.py
irekua_database/models/items/sources.py
irekua_database/models/items/tags.py
irekua_database/models/object_types/__init__.py
irekua_database/models/object_types/annotation_types.py
irekua_database/models/object_types/device_types.py
irekua_database/models/object_types/entailment_types.py
irekua_database/models/object_types/event_types.py
irekua_database/models/object_types/item_types.py
irekua_database/models/object_types/licence_types.py
irekua_database/models/object_types/locality_types.py
irekua_database/models/object_types/mime_types.py
irekua_database/models/object_types/site_descriptor_types.py
irekua_database/models/object_types/site_types.py
irekua_database/models/object_types/term_types.py
irekua_database/models/object_types/data_collections/__init__.py
irekua_database-0.1.1.dist-info/LICENCE
irekua_database-0.1.1.dist-info/METADATA
irekua_database-0.1.1.dist-info/WHEEL
irekua_database-0.1.1.dist-info/top_level.txt
irekua_database-0.1.1.dist-info/RECORD
